wintappy/__init__.py
wintappy/analytics/__init__.py
wintappy/analytics/constants.py
wintappy/analytics/query_analytic.py
wintappy/analytics/utils.py
wintappy/analytics/mitre_car/CAR-2013-02-003.sql
wintappy/analytics/mitre_car/CAR-2013-03-001.sql
wintappy/analytics/mitre_car/CAR-2013-05-004.sql
wintappy/analytics/mitre_car/CAR-2013-07-002.sql
wintappy/analytics/mitre_car/CAR-2014-03-006.sql
wintappy/analytics/mitre_car/CAR-2014-04-003.sql
wintappy/analytics/mitre_car/CAR-2014-05-002.sql
wintappy/analytics/mitre_car/CAR-2014-11-004.sql
wintappy/analytics/mitre_car/CAR-2014-11-006.sql
wintappy/analytics/mitre_car/CAR-2014-11-008.sql
wintappy/analytics/mitre_car/CAR-2016-03-002.sql
wintappy/analytics/mitre_car/CAR-2019-04-002.sql
wintappy/analytics/mitre_car/CAR-2019-04-003.sql
wintappy/analytics/mitre_car/CAR-2019-07-002.sql
wintappy/analytics/mitre_car/CAR-2020-09-002.sql
wintappy/analytics/mitre_car/CAR-2020-09-003.sql
wintappy/analytics/mitre_car/CAR-2020-09-004.sql
wintappy/analytics/mitre_car/CAR-2020-09-005.sql
wintappy/analytics/mitre_car/CAR-2020-11-004.sql
wintappy/analytics/mitre_car/CAR-2020-11-005.sql
wintappy/analytics/mitre_car/CAR-2020-11-006.sql
wintappy/analytics/mitre_car/CAR-2020-11-007.sql
wintappy/analytics/mitre_car/CAR-2020-11-008.sql
wintappy/analytics/mitre_car/CAR-2020-11-009.sql
wintappy/analytics/mitre_car/CAR-2020-11-011.sql
wintappy/analytics/mitre_car/CAR-2021-01-003.sql
wintappy/analytics/mitre_car/CAR-2021-01-004.sql
wintappy/analytics/mitre_car/CAR-2021-01-006.sql
wintappy/analytics/mitre_car/CAR-2021-01-007.sql
wintappy/analytics/mitre_car/CAR-2021-01-008.sql
wintappy/analytics/mitre_car/CAR-2021-02-001.sql
wintappy/analytics/mitre_car/CAR-2021-02-002.sql
wintappy/analytics/mitre_car/CAR-2021-04-001.sql
wintappy/analytics/mitre_car/CAR-2021-05-001.sql
wintappy/analytics/mitre_car/CAR-2021-05-003.sql
wintappy/analytics/mitre_car/CAR-2021-05-006.sql
wintappy/analytics/mitre_car/CAR-2021-05-007.sql
wintappy-0.1.2.dist-info/LICENSE
wintappy-0.1.2.dist-info/METADATA
wintappy-0.1.2.dist-info/WHEEL
wintappy-0.1.2.dist-info/entry_points.txt
wintappy-0.1.2.dist-info/top_level.txt
wintappy-0.1.2.dist-info/RECORD
