Metadata-Version: 2.1
Name: wintappy
Version: 0.1.2
Summary: Python utilities for working with Wintap data
Home-page: https://github.com/LLNL/Wintap-PyUtil
Author: LLNL
Author-email: grantj@llnl.gov
License: MIT License
Requires-Python: >=3.8
License-File: LICENSE
Requires-Dist: altair
Requires-Dist: boto3
Requires-Dist: duckdb
Requires-Dist: fsspec
Requires-Dist: gitpython
Requires-Dist: humanfriendly
Requires-Dist: importlib-resources
Requires-Dist: ipyfilechooser
Requires-Dist: jinja2 ==3.0.3
Requires-Dist: jinjasql
Requires-Dist: lxml
Requires-Dist: magic-duckdb
Requires-Dist: matplotlib
Requires-Dist: mitreattack-python
Requires-Dist: networkx
Requires-Dist: pandas
Requires-Dist: pyarrow
Requires-Dist: python-dotenv
Requires-Dist: pyyaml
Requires-Dist: toml
Requires-Dist: tqdm
